pyneval/__init__.py
pyneval/cli/__init__.py
pyneval/cli/pyneval.py
pyneval/cli/pyneval_tools.py
pyneval/errors/__init__.py
pyneval/errors/exceptions.py
pyneval/metric/__init__.py
pyneval/metric/critical_node_metric.py
pyneval/metric/diadem_metric.py
pyneval/metric/length_metric.py
pyneval/metric/link_metric.py
pyneval/metric/ssd_metric.py
pyneval/metric/volume_metric.py
pyneval/metric/utils/__init__.py
pyneval/metric/utils/anno_utils.py
pyneval/metric/utils/basic_utils.py
pyneval/metric/utils/bigraph_maxmatch_utils.py
pyneval/metric/utils/bin_utils.py
pyneval/metric/utils/cli_utils.py
pyneval/metric/utils/config_utils.py
pyneval/metric/utils/diadam_match_utils.py
pyneval/metric/utils/edge_match_utils.py
pyneval/metric/utils/km_utils.py
pyneval/metric/utils/metric_manager.py
pyneval/metric/utils/point_match_utils.py
pyneval/metric/utils/tiff_utils.py
pyneval/metric/utils/klib/TiffFile.py
pyneval/metric/utils/klib/__init__.py
pyneval/metric/utils/klib/baseio.py
pyneval/metric/utils/klib/simulator.py
pyneval/model/__init__.py
pyneval/model/binary_node.py
pyneval/model/euclidean_point.py
pyneval/model/swc_node.py
pyneval/model/swc_tree.py
pyneval/pyneval_io/__init__.py
pyneval/pyneval_io/json_io.py
pyneval/pyneval_io/swc_io.py
pyneval/pyneval_io/tiff_io.py
pyneval/tools/__init__.py
pyneval/tools/overlap_detect.py
pyneval/tools/re_sample.py
pyneval/tools/swc_cut.py
pyneval/tools/tiff_cut.py
pyneval/tools/optimize/SA.py
pyneval/tools/optimize/__init__.py
pyneval/tools/optimize/optimize.py
pyneval-1.1.1.dist-info/LICENSE.txt
pyneval-1.1.1.dist-info/METADATA
pyneval-1.1.1.dist-info/WHEEL
pyneval-1.1.1.dist-info/entry_points.txt
pyneval-1.1.1.dist-info/top_level.txt
pyneval-1.1.1.dist-info/RECORD
